setup.cfg
setup.py
lib/constrictor/__init__.py
lib/constrictor.egg-info/PKG-INFO
lib/constrictor.egg-info/SOURCES.txt
lib/constrictor.egg-info/dependency_links.txt
lib/constrictor.egg-info/not-zip-safe
lib/constrictor.egg-info/top_level.txt