Metadata-Version: 1.0
Name: constrictor
Version: 1.0
Summary: Simpler, better, and streaming gzip handling
Home-page: https://github.com/f0rk/constrictor
Author: Ryan P. Kelly
Author-email: ryan@ryankelly.us
License: UNKNOWN
Platform: UNKNOWN
